pyephem_sunpath/__init__.py
pyephem_sunpath/sunpath.py
pyephem_sunpath-0.2.4.dist-info/METADATA
pyephem_sunpath-0.2.4.dist-info/WHEEL
pyephem_sunpath-0.2.4.dist-info/licenses/AUTHORS.rst
pyephem_sunpath-0.2.4.dist-info/licenses/LICENSE
pyephem_sunpath-0.2.4.dist-info/RECORD
