Metadata-Version: 2.4
Name: pyephem-sunpath
Version: 0.2.4
Summary: Calculate sunpath using pyephem
Project-URL: Homepage, https://github.com/santoshphilip/pyephem_sunpath
Project-URL: Repository, https://github.com/santoshphilip/pyephem_sunpath
Project-URL: Issues, https://github.com/santoshphilip/pyephem_sunpath/issues
Author-email: Santosh Philip <santosh_philip@nomail.com>
License: LGPLv3
License-File: AUTHORS.rst
License-File: LICENSE
Keywords: pyephem-sunpath,pyephem_sunpath,solar,sunpath
Classifier: Development Status :: 4 - Beta
Classifier: Intended Audience :: Developers
Classifier: Intended Audience :: Science/Research
Classifier: License :: OSI Approved :: GNU Lesser General Public License v3 (LGPLv3)
Classifier: Natural Language :: English
Requires-Python: >=3.9
Requires-Dist: pyephem>=9.99
